{"candles": [{"time": "2026-02-16", "open": 300.0, "high": 330.0, "low": 300.0, "close": 330.0}, {"time": "2026-02-17", "open": 328.0, "high": 361.8, "low": 328.0, "close": 361.8}, {"time": "2026-02-22", "open": 358.2, "high": 395.3, "low": 358.2, "close": 395.3}, {"time": "2026-02-23", "open": 391.5, "high": 432.0, "low": 391.5, "close": 432.0}, {"time": "2026-02-24", "open": 427.9, "high": 472.2, "low": 427.9, "close": 472.2}, {"time": "2026-02-25", "open": 467.5, "high": 519.4, "low": 467.5, "close": 519.4}, {"time": "2026-02-26", "open": 514.3, "high": 567.5, "low": 514.3, "close": 567.5}, {"time": "2026-03-01", "open": 561.9, "high": 624.2, "low": 561.9, "close": 624.2}, {"time": "2026-03-03", "open": 621.1, "high": 685.5, "low": 621.1, "close": 685.5}, {"time": "2026-03-09", "open": 675.3, "high": 675.3, "low": 675.3, "close": 675.3}, {"time": "2026-03-10", "open": 688.8, "high": 742.8, "low": 688.8, "close": 742.8}, {"time": "2026-03-11", "open": 735.6, "high": 812.1, "low": 735.6, "close": 812.1}, {"time": "2026-03-12", "open": 802.1, "high": 893.3, "low": 802.1, "close": 893.3}, {"time": "2026-03-15", "open": 885.2, "high": 939.3, "low": 885.2, "close": 939.3}, {"time": "2026-03-16", "open": 921.2, "high": 1033.2, "low": 921.2, "close": 1033.2}, {"time": "2026-03-17", "open": 1017.8, "high": 1136.5, "low": 1017.8, "close": 1136.5}, {"time": "2026-03-19", "open": 1120.5, "high": 1250.1, "low": 1120.5, "close": 1250.1}, {"time": "2026-03-22", "open": 1235.0, "high": 1375.1, "low": 1235.0, "close": 1375.1}, {"time": "2026-03-23", "open": 1361.4, "high": 1512.6, "low": 1361.4, "close": 1512.6}, {"time": "2026-03-24", "open": 1494.4, "high": 1663.8, "low": 1494.4, "close": 1663.8}, {"time": "2026-03-25", "open": 1697.0, "high": 1830.1, "low": 1697.0, "close": 1830.1}, {"time": "2026-03-26", "open": 1821.0, "high": 2013.1, "low": 1821.0, "close": 2013.1}, {"time": "2026-03-27", "open": 1821.0, "high": 2013.1, "low": 1821.0, "close": 2013.1}, {"time": "2026-03-30", "open": 2203.9, "high": 2435.8, "low": 2203.9, "close": 2435.8}, {"time": "2026-03-31", "open": 2430.1, "high": 2679.3, "low": 2430.1, "close": 2679.3}, {"time": "2026-04-01", "open": 2678.2, "high": 2947.2, "low": 2678.2, "close": 2947.2}, {"time": "2026-04-06", "open": 3637.3, "high": 3922.6, "low": 3210.0, "close": 3509.0}, {"time": "2026-04-07", "open": 3509.0, "high": 3650.0, "low": 3440.0, "close": 3545.0}, {"time": "2026-04-08", "open": 3545.0, "high": 3899.5, "low": 3545.0, "close": 3899.5}, {"time": "2026-04-09", "open": 3977.0, "high": 4289.4, "low": 3825.0, "close": 4289.4}, {"time": "2026-04-12", "open": 4375.1, "high": 4718.3, "low": 4375.1, "close": 4691.0}, {"time": "2026-04-13", "open": 4775.4, "high": 5049.0, "low": 4611.0, "close": 4799.0}, {"time": "2026-04-14", "open": 4775.4, "high": 5049.0, "low": 4611.0, "close": 4799.0}, {"time": "2026-04-15", "open": 4799.0, "high": 4896.0, "low": 4500.0, "close": 4530.0}, {"time": "2026-04-16", "open": 4501.0, "high": 4600.0, "low": 4280.0, "close": 4366.0}, {"time": "2026-04-19", "open": 4400.0, "high": 4730.0, "low": 4300.0, "close": 4649.1}, {"time": "2026-04-20", "open": 4700.0, "high": 4700.0, "low": 4465.0, "close": 4479.0}, {"time": "2026-04-21", "open": 4390.1, "high": 4539.9, "low": 4210.0, "close": 4290.0}, {"time": "2026-04-22", "open": 4080.0, "high": 4326.0, "low": 4080.0, "close": 4230.0}, {"time": "2026-04-23", "open": 4180.0, "high": 4425.0, "low": 4070.0, "close": 4320.0}, {"time": "2026-04-26", "open": 4291.0, "high": 4330.0, "low": 4200.0, "close": 4220.0}, {"time": "2026-04-27", "open": 4203.0, "high": 4346.0, "low": 4195.0, "close": 4239.0}, {"time": "2026-04-28", "open": 4239.0, "high": 4270.0, "low": 3981.0, "close": 4000.0}, {"time": "2026-04-29", "open": 4000.0, "high": 4000.0, "low": 3790.0, "close": 3810.1}, {"time": "2026-04-30", "open": 3780.0, "high": 3989.0, "low": 3700.0, "close": 3850.2}, {"time": "2026-05-03", "open": 3780.0, "high": 3989.0, "low": 3700.0, "close": 3850.2}, {"time": "2026-05-04", "open": 3865.0, "high": 3949.0, "low": 3850.0, "close": 3900.0}], "volumes": [{"time": "2026-02-16", "value": 130, "color": "rgba(0,228,117,0.5)"}, {"time": "2026-02-17", "value": 60, "color": "rgba(0,228,117,0.5)"}, {"time": "2026-02-22", "value": 60, "color": "rgba(0,228,117,0.5)"}, {"time": "2026-02-23", "value": 60, "color": "rgba(0,228,117,0.5)"}, {"time": "2026-02-24", "value": 60, "color": "rgba(0,228,117,0.5)"}, {"time": "2026-02-25", "value": 60, "color": "rgba(0,228,117,0.5)"}, {"time": "2026-02-26", "value": 60, "color": "rgba(0,228,117,0.5)"}, {"time": "2026-03-01", "value": 110, "color": "rgba(0,228,117,0.5)"}, {"time": "2026-03-03", "value": 60, "color": "rgba(0,228,117,0.5)"}, {"time": "2026-03-09", "value": 10, "color": "rgba(0,228,117,0.5)"}, {"time": "2026-03-10", "value": 80, "color": "rgba(0,228,117,0.5)"}, {"time": "2026-03-11", "value": 60, "color": "rgba(0,228,117,0.5)"}, {"time": "2026-03-12", "value": 160, "color": "rgba(0,228,117,0.5)"}, {"time": "2026-03-15", "value": 80, "color": "rgba(0,228,117,0.5)"}, {"time": "2026-03-16", "value": 170, "color": "rgba(0,228,117,0.5)"}, {"time": "2026-03-17", "value": 250, "color": "rgba(0,228,117,0.5)"}, {"time": "2026-03-19", "value": 770, "color": "rgba(0,228,117,0.5)"}, {"time": "2026-03-22", "value": 375, "color": "rgba(0,228,117,0.5)"}, {"time": "2026-03-23", "value": 480, "color": "rgba(0,228,117,0.5)"}, {"time": "2026-03-24", "value": 543, "color": "rgba(0,228,117,0.5)"}, {"time": "2026-03-25", "value": 1020, "color": "rgba(0,228,117,0.5)"}, {"time": "2026-03-26", "value": 3368, "color": "rgba(0,228,117,0.5)"}, {"time": "2026-03-27", "value": 3368, "color": "rgba(0,228,117,0.5)"}, {"time": "2026-03-30", "value": 2297, "color": "rgba(0,228,117,0.5)"}, {"time": "2026-03-31", "value": 2107, "color": "rgba(0,228,117,0.5)"}, {"time": "2026-04-01", "value": 5120, "color": "rgba(0,228,117,0.5)"}, {"time": "2026-04-06", "value": 326117, "color": "rgba(255,82,82,0.5)"}, {"time": "2026-04-07", "value": 68424, "color": "rgba(0,228,117,0.5)"}, {"time": "2026-04-08", "value": 110003, "color": "rgba(0,228,117,0.5)"}, {"time": "2026-04-09", "value": 68240, "color": "rgba(0,228,117,0.5)"}, {"time": "2026-04-12", "value": 93429, "color": "rgba(0,228,117,0.5)"}, {"time": "2026-04-13", "value": 94947, "color": "rgba(0,228,117,0.5)"}, {"time": "2026-04-14", "value": 94947, "color": "rgba(0,228,117,0.5)"}, {"time": "2026-04-15", "value": 106020, "color": "rgba(255,82,82,0.5)"}, {"time": "2026-04-16", "value": 140365, "color": "rgba(255,82,82,0.5)"}, {"time": "2026-04-19", "value": 72648, "color": "rgba(0,228,117,0.5)"}, {"time": "2026-04-20", "value": 42038, "color": "rgba(255,82,82,0.5)"}, {"time": "2026-04-21", "value": 68901, "color": "rgba(255,82,82,0.5)"}, {"time": "2026-04-22", "value": 78442, "color": "rgba(0,228,117,0.5)"}, {"time": "2026-04-23", "value": 70488, "color": "rgba(0,228,117,0.5)"}, {"time": "2026-04-26", "value": 58569, "color": "rgba(255,82,82,0.5)"}, {"time": "2026-04-27", "value": 72187, "color": "rgba(0,228,117,0.5)"}, {"time": "2026-04-28", "value": 85116, "color": "rgba(255,82,82,0.5)"}, {"time": "2026-04-29", "value": 62734, "color": "rgba(255,82,82,0.5)"}, {"time": "2026-04-30", "value": 70158, "color": "rgba(0,228,117,0.5)"}, {"time": "2026-05-03", "value": 70158, "color": "rgba(0,228,117,0.5)"}, {"time": "2026-05-04", "value": 8701, "color": "rgba(0,228,117,0.5)"}]}