{"candles": [{"time": "2024-09-02", "open": 9.8, "high": 9.9, "low": 9.3, "close": 9.7}, {"time": "2024-09-03", "open": 9.6, "high": 9.7, "low": 9.6, "close": 9.7}, {"time": "2024-09-04", "open": 9.5, "high": 9.6, "low": 9.5, "close": 9.5}, {"time": "2024-09-05", "open": 9.7, "high": 9.9, "low": 9.6, "close": 9.6}, {"time": "2024-09-08", "open": 9.7, "high": 9.8, "low": 9.7, "close": 9.8}, {"time": "2024-09-09", "open": 9.7, "high": 9.7, "low": 9.5, "close": 9.5}, {"time": "2024-09-10", "open": 9.3, "high": 9.3, "low": 9.3, "close": 9.3}, {"time": "2024-09-12", "open": 9.2, "high": 9.5, "low": 9.2, "close": 9.5}, {"time": "2024-09-15", "open": 9.7, "high": 9.7, "low": 9.3, "close": 9.3}, {"time": "2024-09-16", "open": 9.2, "high": 9.2, "low": 9.1, "close": 9.1}, {"time": "2024-09-18", "open": 9.0, "high": 9.0, "low": 8.6, "close": 8.6}, {"time": "2024-09-22", "open": 8.8, "high": 9.5, "low": 8.8, "close": 9.2}, {"time": "2024-09-23", "open": 9.4, "high": 9.6, "low": 9.4, "close": 9.6}, {"time": "2024-09-24", "open": 9.4, "high": 9.4, "low": 9.0, "close": 9.0}, {"time": "2024-09-25", "open": 9.0, "high": 9.0, "low": 9.0, "close": 9.0}, {"time": "2024-09-26", "open": 9.0, "high": 9.0, "low": 9.0, "close": 9.0}, {"time": "2024-09-30", "open": 9.2, "high": 9.4, "low": 9.2, "close": 9.3}, {"time": "2024-10-01", "open": 9.1, "high": 9.4, "low": 9.1, "close": 9.4}, {"time": "2024-10-02", "open": 9.3, "high": 9.3, "low": 9.0, "close": 9.0}, {"time": "2024-10-06", "open": 9.0, "high": 9.2, "low": 9.0, "close": 9.2}, {"time": "2024-10-07", "open": 9.3, "high": 9.3, "low": 9.0, "close": 9.0}, {"time": "2024-10-08", "open": 8.8, "high": 9.2, "low": 8.8, "close": 9.2}, {"time": "2024-10-15", "open": 9.2, "high": 9.3, "low": 9.1, "close": 9.3}, {"time": "2024-10-16", "open": 9.2, "high": 9.7, "low": 9.2, "close": 9.6}, {"time": "2024-10-17", "open": 9.8, "high": 9.8, "low": 9.6, "close": 9.7}, {"time": "2024-10-20", "open": 9.9, "high": 9.9, "low": 9.6, "close": 9.8}, {"time": "2024-10-21", "open": 9.9, "high": 10.0, "low": 9.7, "close": 9.9}, {"time": "2024-10-22", "open": 10.1, "high": 10.1, "low": 9.8, "close": 10.1}, {"time": "2024-10-23", "open": 10.2, "high": 10.2, "low": 10.1, "close": 10.1}, {"time": "2024-10-24", "open": 10.2, "high": 10.2, "low": 9.8, "close": 10.1}, {"time": "2024-10-27", "open": 10.2, "high": 10.2, "low": 9.9, "close": 9.9}, {"time": "2024-10-28", "open": 10.1, "high": 10.1, "low": 9.7, "close": 9.9}, {"time": "2024-10-29", "open": 10.0, "high": 10.0, "low": 9.8, "close": 10.0}, {"time": "2024-11-06", "open": 10.2, "high": 10.2, "low": 10.2, "close": 10.2}, {"time": "2024-11-10", "open": 10.4, "high": 10.4, "low": 9.8, "close": 9.9}, {"time": "2024-11-11", "open": 9.8, "high": 10.0, "low": 9.8, "close": 10.0}, {"time": "2024-11-12", "open": 9.8, "high": 10.0, "low": 9.8, "close": 9.8}, {"time": "2024-11-13", "open": 10.0, "high": 10.0, "low": 9.7, "close": 9.8}, {"time": "2024-11-14", "open": 9.6, "high": 9.8, "low": 9.6, "close": 9.8}, {"time": "2024-11-17", "open": 9.9, "high": 9.9, "low": 9.6, "close": 9.7}, {"time": "2024-11-19", "open": 9.7, "high": 9.9, "low": 9.7, "close": 9.7}, {"time": "2024-11-20", "open": 9.8, "high": 10.0, "low": 9.8, "close": 10.0}, {"time": "2024-11-21", "open": 9.8, "high": 9.9, "low": 9.8, "close": 9.8}, {"time": "2024-11-24", "open": 9.8, "high": 9.8, "low": 9.8, "close": 9.8}, {"time": "2024-11-25", "open": 9.8, "high": 10.0, "low": 9.8, "close": 9.8}, {"time": "2024-11-26", "open": 9.9, "high": 9.9, "low": 9.8, "close": 9.9}, {"time": "2024-11-27", "open": 9.8, "high": 9.9, "low": 9.8, "close": 9.8}, {"time": "2024-11-28", "open": 9.8, "high": 10.0, "low": 9.8, "close": 10.0}, {"time": "2024-12-01", "open": 10.0, "high": 10.0, "low": 9.8, "close": 10.0}, {"time": "2024-12-02", "open": 9.9, "high": 10.0, "low": 9.8, "close": 10.0}, {"time": "2024-12-03", "open": 10.0, "high": 10.1, "low": 10.0, "close": 10.0}, {"time": "2024-12-04", "open": 10.0, "high": 10.0, "low": 9.9, "close": 10.0}, {"time": "2024-12-05", "open": 9.8, "high": 10.0, "low": 9.8, "close": 9.8}, {"time": "2024-12-08", "open": 10.0, "high": 10.0, "low": 9.6, "close": 9.6}, {"time": "2024-12-09", "open": 9.8, "high": 9.9, "low": 9.8, "close": 9.9}, {"time": "2024-12-10", "open": 9.7, "high": 9.7, "low": 9.7, "close": 9.7}, {"time": "2024-12-11", "open": 9.9, "high": 9.9, "low": 9.7, "close": 9.7}, {"time": "2024-12-12", "open": 9.6, "high": 9.8, "low": 9.6, "close": 9.8}, {"time": "2024-12-16", "open": 9.7, "high": 9.7, "low": 9.5, "close": 9.7}, {"time": "2024-12-17", "open": 9.8, "high": 9.8, "low": 9.6, "close": 9.6}, {"time": "2024-12-18", "open": 9.6, "high": 9.6, "low": 9.5, "close": 9.5}, {"time": "2024-12-19", "open": 9.7, "high": 9.7, "low": 9.7, "close": 9.7}, {"time": "2024-12-23", "open": 9.8, "high": 9.9, "low": 9.5, "close": 9.7}, {"time": "2024-12-24", "open": 9.6, "high": 9.6, "low": 9.5, "close": 9.5}, {"time": "2024-12-26", "open": 9.3, "high": 9.6, "low": 9.3, "close": 9.6}, {"time": "2024-12-29", "open": 9.4, "high": 9.6, "low": 9.4, "close": 9.4}, {"time": "2024-12-31", "open": 9.6, "high": 9.6, "low": 9.6, "close": 9.6}, {"time": "2025-01-01", "open": 9.8, "high": 9.8, "low": 9.5, "close": 9.5}, {"time": "2025-01-02", "open": 9.5, "high": 9.8, "low": 9.5, "close": 9.8}, {"time": "2025-01-05", "open": 9.6, "high": 9.6, "low": 9.6, "close": 9.6}, {"time": "2025-01-06", "open": 9.6, "high": 10.0, "low": 9.6, "close": 10.0}, {"time": "2025-01-07", "open": 9.8, "high": 9.9, "low": 9.8, "close": 9.8}, {"time": "2025-01-08", "open": 9.8, "high": 9.9, "low": 9.6, "close": 9.6}, {"time": "2025-01-09", "open": 9.6, "high": 9.6, "low": 9.5, "close": 9.5}, {"time": "2025-01-12", "open": 9.7, "high": 9.8, "low": 9.7, "close": 9.8}, {"time": "2025-01-13", "open": 10.0, "high": 10.0, "low": 9.7, "close": 9.7}, {"time": "2025-01-15", "open": 9.8, "high": 9.8, "low": 9.8, "close": 9.8}, {"time": "2025-01-19", "open": 10.0, "high": 10.0, "low": 10.0, "close": 10.0}, {"time": "2025-01-20", "open": 9.8, "high": 9.8, "low": 9.7, "close": 9.8}, {"time": "2025-01-21", "open": 9.6, "high": 9.8, "low": 9.4, "close": 9.4}, {"time": "2025-01-22", "open": 9.4, "high": 9.6, "low": 9.4, "close": 9.4}, {"time": "2025-01-23", "open": 9.6, "high": 9.6, "low": 9.6, "close": 9.6}, {"time": "2025-01-26", "open": 9.6, "high": 9.8, "low": 9.6, "close": 9.8}, {"time": "2025-01-27", "open": 9.9, "high": 9.9, "low": 9.4, "close": 9.4}, {"time": "2025-01-28", "open": 9.6, "high": 9.6, "low": 9.6, "close": 9.6}, {"time": "2025-02-02", "open": 9.4, "high": 9.6, "low": 9.4, "close": 9.5}, {"time": "2025-02-03", "open": 9.7, "high": 9.7, "low": 9.6, "close": 9.7}, {"time": "2025-02-04", "open": 9.5, "high": 9.6, "low": 9.5, "close": 9.6}, {"time": "2025-02-05", "open": 9.7, "high": 9.7, "low": 9.5, "close": 9.6}, {"time": "2025-02-06", "open": 9.5, "high": 9.6, "low": 9.5, "close": 9.6}, {"time": "2025-02-09", "open": 9.5, "high": 9.6, "low": 9.5, "close": 9.6}, {"time": "2025-02-11", "open": 9.6, "high": 9.6, "low": 9.5, "close": 9.6}, {"time": "2025-02-12", "open": 9.6, "high": 9.7, "low": 9.6, "close": 9.7}, {"time": "2025-02-13", "open": 9.8, "high": 9.8, "low": 9.8, "close": 9.8}, {"time": "2025-02-16", "open": 9.6, "high": 9.6, "low": 9.6, "close": 9.6}, {"time": "2025-02-17", "open": 9.5, "high": 9.5, "low": 9.5, "close": 9.5}, {"time": "2025-02-18", "open": 9.5, "high": 9.7, "low": 9.5, "close": 9.7}, {"time": "2025-02-20", "open": 9.5, "high": 9.6, "low": 9.5, "close": 9.6}, {"time": "2025-02-23", "open": 9.6, "high": 9.6, "low": 9.6, "close": 9.6}, {"time": "2025-02-24", "open": 9.6, "high": 9.7, "low": 9.6, "close": 9.7}, {"time": "2025-02-25", "open": 9.6, "high": 9.6, "low": 9.6, "close": 9.6}, {"time": "2025-02-27", "open": 9.8, "high": 9.8, "low": 9.6, "close": 9.6}, {"time": "2025-03-02", "open": 9.8, "high": 9.9, "low": 9.8, "close": 9.9}, {"time": "2025-03-03", "open": 9.9, "high": 10.0, "low": 9.8, "close": 9.8}, {"time": "2025-03-04", "open": 10.0, "high": 10.0, "low": 9.8, "close": 10.0}, {"time": "2025-03-05", "open": 9.8, "high": 10.0, "low": 9.8, "close": 10.0}, {"time": "2025-03-06", "open": 10.0, "high": 10.0, "low": 9.9, "close": 10.0}, {"time": "2025-03-09", "open": 9.8, "high": 10.0, "low": 9.8, "close": 9.9}, {"time": "2025-03-11", "open": 9.8, "high": 9.8, "low": 9.8, "close": 9.8}, {"time": "2025-03-12", "open": 9.6, "high": 9.8, "low": 9.6, "close": 9.7}, {"time": "2025-03-16", "open": 9.8, "high": 9.8, "low": 9.8, "close": 9.8}, {"time": "2025-03-17", "open": 9.9, "high": 9.9, "low": 9.7, "close": 9.7}, {"time": "2025-03-18", "open": 9.8, "high": 9.8, "low": 9.6, "close": 9.7}, {"time": "2025-03-19", "open": 9.9, "high": 9.9, "low": 9.7, "close": 9.7}, {"time": "2025-03-20", "open": 9.8, "high": 10.0, "low": 9.7, "close": 9.7}, {"time": "2025-03-23", "open": 9.9, "high": 9.9, "low": 9.6, "close": 9.6}, {"time": "2025-03-24", "open": 9.5, "high": 9.8, "low": 9.5, "close": 9.8}, {"time": "2025-03-25", "open": 9.6, "high": 9.8, "low": 9.6, "close": 9.6}, {"time": "2025-03-26", "open": 9.5, "high": 9.7, "low": 9.5, "close": 9.6}, {"time": "2025-03-27", "open": 9.8, "high": 9.8, "low": 9.7, "close": 9.7}, {"time": "2025-03-30", "open": 9.6, "high": 9.6, "low": 9.6, "close": 9.6}, {"time": "2025-04-01", "open": 9.4, "high": 9.8, "low": 9.4, "close": 9.7}, {"time": "2025-04-02", "open": 9.9, "high": 9.9, "low": 9.7, "close": 9.9}, {"time": "2025-04-03", "open": 9.8, "high": 10.1, "low": 9.8, "close": 10.0}, {"time": "2025-04-07", "open": 9.8, "high": 9.8, "low": 9.6, "close": 9.8}, {"time": "2025-04-08", "open": 9.7, "high": 9.8, "low": 9.7, "close": 9.8}, {"time": "2025-04-09", "open": 10.0, "high": 10.0, "low": 9.9, "close": 9.9}, {"time": "2025-04-10", "open": 9.9, "high": 10.1, "low": 9.9, "close": 10.1}, {"time": "2025-04-13", "open": 10.2, "high": 10.2, "low": 10.0, "close": 10.0}, {"time": "2025-04-15", "open": 9.9, "high": 10.0, "low": 9.9, "close": 10.0}, {"time": "2025-04-16", "open": 10.0, "high": 10.0, "low": 10.0, "close": 10.0}, {"time": "2025-04-17", "open": 10.1, "high": 10.1, "low": 10.1, "close": 10.1}, {"time": "2025-04-20", "open": 9.9, "high": 10.2, "low": 9.9, "close": 10.0}, {"time": "2025-04-21", "open": 9.8, "high": 9.8, "low": 9.8, "close": 9.8}, {"time": "2025-04-22", "open": 9.9, "high": 10.0, "low": 9.9, "close": 10.0}, {"time": "2025-04-23", "open": 10.2, "high": 10.2, "low": 10.0, "close": 10.0}, {"time": "2025-04-24", "open": 10.2, "high": 10.2, "low": 10.0, "close": 10.1}, {"time": "2025-04-27", "open": 10.1, "high": 10.4, "low": 10.1, "close": 10.4}, {"time": "2025-04-28", "open": 10.2, "high": 10.2, "low": 10.0, "close": 10.1}, {"time": "2025-04-29", "open": 10.0, "high": 10.1, "low": 10.0, "close": 10.0}, {"time": "2025-04-30", "open": 10.0, "high": 10.2, "low": 10.0, "close": 10.2}, {"time": "2025-05-04", "open": 10.0, "high": 10.0, "low": 10.0, "close": 10.0}, {"time": "2025-05-05", "open": 9.8, "high": 9.8, "low": 9.8, "close": 9.8}, {"time": "2025-05-06", "open": 9.9, "high": 10.0, "low": 9.8, "close": 10.0}, {"time": "2025-05-07", "open": 9.9, "high": 9.9, "low": 9.9, "close": 9.9}, {"time": "2025-05-08", "open": 10.1, "high": 10.3, "low": 10.1, "close": 10.3}, {"time": "2025-05-11", "open": 10.1, "high": 10.3, "low": 10.1, "close": 10.3}, {"time": "2025-05-13", "open": 10.5, "high": 10.5, "low": 10.5, "close": 10.5}, {"time": "2025-05-15", "open": 10.3, "high": 10.3, "low": 10.3, "close": 10.3}, {"time": "2025-05-18", "open": 10.1, "high": 10.3, "low": 10.1, "close": 10.2}, {"time": "2025-05-19", "open": 10.2, "high": 10.2, "low": 10.0, "close": 10.2}, {"time": "2025-05-21", "open": 10.3, "high": 10.3, "low": 10.3, "close": 10.3}, {"time": "2025-05-22", "open": 10.1, "high": 10.3, "low": 10.1, "close": 10.2}, {"time": "2025-05-25", "open": 10.0, "high": 10.2, "low": 10.0, "close": 10.2}, {"time": "2025-05-26", "open": 10.1, "high": 10.2, "low": 9.9, "close": 10.2}, {"time": "2025-05-27", "open": 10.0, "high": 10.0, "low": 10.0, "close": 10.0}, {"time": "2025-05-28", "open": 9.8, "high": 10.0, "low": 9.8, "close": 9.9}, {"time": "2025-06-02", "open": 9.9, "high": 9.9, "low": 9.9, "close": 9.9}, {"time": "2025-06-03", "open": 9.8, "high": 10.0, "low": 9.8, "close": 9.9}, {"time": "2025-06-04", "open": 9.8, "high": 10.2, "low": 9.8, "close": 10.1}, {"time": "2025-06-05", "open": 10.1, "high": 10.1, "low": 9.9, "close": 9.9}, {"time": "2025-06-08", "open": 10.0, "high": 10.0, "low": 9.9, "close": 9.9}, {"time": "2025-06-09", "open": 9.9, "high": 9.9, "low": 9.9, "close": 9.9}, {"time": "2025-06-10", "open": 10.1, "high": 10.2, "low": 10.0, "close": 10.0}, {"time": "2025-06-11", "open": 10.0, "high": 10.2, "low": 9.8, "close": 10.0}, {"time": "2025-06-12", "open": 9.9, "high": 10.1, "low": 9.9, "close": 9.9}, {"time": "2025-06-16", "open": 9.8, "high": 9.9, "low": 9.8, "close": 9.9}, {"time": "2025-06-17", "open": 9.8, "high": 10.0, "low": 9.8, "close": 9.8}, {"time": "2025-06-18", "open": 10.0, "high": 10.0, "low": 9.8, "close": 9.8}, {"time": "2025-06-19", "open": 10.0, "high": 10.0, "low": 10.0, "close": 10.0}, {"time": "2025-06-22", "open": 10.1, "high": 10.1, "low": 9.9, "close": 9.9}, {"time": "2025-06-23", "open": 10.0, "high": 10.0, "low": 9.9, "close": 10.0}, {"time": "2025-06-24", "open": 10.0, "high": 10.0, "low": 10.0, "close": 10.0}, {"time": "2025-06-25", "open": 10.0, "high": 10.0, "low": 9.8, "close": 9.8}, {"time": "2025-06-26", "open": 10.0, "high": 10.0, "low": 10.0, "close": 10.0}, {"time": "2025-06-29", "open": 9.9, "high": 10.2, "low": 9.9, "close": 10.2}, {"time": "2025-06-30", "open": 10.0, "high": 10.0, "low": 10.0, "close": 10.0}, {"time": "2025-07-01", "open": 10.2, "high": 10.2, "low": 10.0, "close": 10.1}, {"time": "2025-07-02", "open": 10.0, "high": 10.2, "low": 10.0, "close": 10.1}, {"time": "2025-07-03", "open": 10.0, "high": 10.0, "low": 10.0, "close": 10.0}, {"time": "2025-07-06", "open": 10.2, "high": 10.3, "low": 10.1, "close": 10.3}, {"time": "2025-07-07", "open": 10.3, "high": 10.3, "low": 10.2, "close": 10.2}, {"time": "2025-07-08", "open": 10.1, "high": 10.1, "low": 10.1, "close": 10.1}, {"time": "2025-07-09", "open": 10.3, "high": 10.4, "low": 10.2, "close": 10.2}, {"time": "2025-07-10", "open": 10.3, "high": 10.5, "low": 10.2, "close": 10.3}, {"time": "2025-07-13", "open": 10.3, "high": 10.4, "low": 10.3, "close": 10.3}, {"time": "2025-07-14", "open": 10.4, "high": 10.5, "low": 10.3, "close": 10.4}, {"time": "2025-07-15", "open": 10.3, "high": 10.4, "low": 10.2, "close": 10.4}, {"time": "2025-07-16", "open": 10.6, "high": 10.6, "low": 10.3, "close": 10.5}, {"time": "2025-07-17", "open": 10.3, "high": 10.6, "low": 10.3, "close": 10.6}, {"time": "2025-07-20", "open": 10.4, "high": 10.7, "low": 10.4, "close": 10.7}, {"time": "2025-07-21", "open": 10.5, "high": 10.7, "low": 10.5, "close": 10.6}, {"time": "2025-07-22", "open": 10.7, "high": 10.8, "low": 10.6, "close": 10.8}, {"time": "2025-07-23", "open": 10.6, "high": 10.8, "low": 10.6, "close": 10.7}, {"time": "2025-07-24", "open": 10.5, "high": 10.7, "low": 10.5, "close": 10.6}, {"time": "2025-07-27", "open": 10.4, "high": 10.9, "low": 10.4, "close": 10.8}, {"time": "2025-07-28", "open": 10.9, "high": 11.0, "low": 10.9, "close": 11.0}, {"time": "2025-07-29", "open": 10.8, "high": 10.9, "low": 10.8, "close": 10.8}, {"time": "2025-07-30", "open": 11.1, "high": 11.1, "low": 10.7, "close": 10.7}, {"time": "2025-07-31", "open": 10.7, "high": 11.1, "low": 10.6, "close": 10.9}, {"time": "2025-08-03", "open": 11.1, "high": 11.1, "low": 10.8, "close": 10.8}, {"time": "2025-08-04", "open": 10.6, "high": 10.8, "low": 10.6, "close": 10.8}, {"time": "2025-08-05", "open": 10.7, "high": 10.8, "low": 10.7, "close": 10.8}, {"time": "2025-08-06", "open": 10.7, "high": 10.7, "low": 10.7, "close": 10.7}, {"time": "2025-08-07", "open": 10.5, "high": 10.9, "low": 10.5, "close": 10.8}, {"time": "2025-08-11", "open": 10.8, "high": 11.3, "low": 10.8, "close": 11.3}, {"time": "2025-08-12", "open": 11.3, "high": 11.4, "low": 11.3, "close": 11.4}, {"time": "2025-08-13", "open": 11.4, "high": 11.4, "low": 11.3, "close": 11.4}, {"time": "2025-08-14", "open": 11.4, "high": 11.4, "low": 11.2, "close": 11.2}, {"time": "2025-08-17", "open": 11.1, "high": 11.6, "low": 11.1, "close": 11.6}, {"time": "2025-08-18", "open": 11.4, "high": 11.6, "low": 11.2, "close": 11.3}, {"time": "2025-08-19", "open": 11.3, "high": 11.5, "low": 11.3, "close": 11.4}, {"time": "2025-08-20", "open": 11.6, "high": 11.6, "low": 11.4, "close": 11.4}, {"time": "2025-08-21", "open": 11.5, "high": 11.7, "low": 11.4, "close": 11.5}, {"time": "2025-08-24", "open": 9.3, "high": 9.3, "low": 9.0, "close": 9.2}, {"time": "2025-08-25", "open": 9.3, "high": 9.3, "low": 9.2, "close": 9.3}, {"time": "2025-08-26", "open": 9.4, "high": 9.5, "low": 9.3, "close": 9.5}, {"time": "2025-08-27", "open": 9.7, "high": 9.7, "low": 9.7, "close": 9.7}, {"time": "2025-08-28", "open": 9.9, "high": 10.0, "low": 9.7, "close": 9.7}, {"time": "2025-08-31", "open": 9.8, "high": 9.8, "low": 9.8, "close": 9.8}, {"time": "2025-09-01", "open": 9.6, "high": 9.6, "low": 9.4, "close": 9.5}, {"time": "2025-09-02", "open": 9.7, "high": 9.7, "low": 9.7, "close": 9.7}, {"time": "2025-09-03", "open": 9.5, "high": 9.5, "low": 9.3, "close": 9.3}, {"time": "2025-09-04", "open": 9.4, "high": 9.5, "low": 9.4, "close": 9.5}, {"time": "2025-09-07", "open": 9.5, "high": 9.5, "low": 9.5, "close": 9.5}, {"time": "2025-09-08", "open": 9.5, "high": 9.5, "low": 9.2, "close": 9.2}, {"time": "2025-09-21", "open": 9.1, "high": 9.1, "low": 9.1, "close": 9.1}, {"time": "2025-09-23", "open": 9.2, "high": 9.2, "low": 9.2, "close": 9.2}, {"time": "2025-09-24", "open": 9.1, "high": 9.6, "low": 8.9, "close": 9.6}, {"time": "2025-09-25", "open": 9.6, "high": 10.0, "low": 9.6, "close": 9.7}, {"time": "2025-09-28", "open": 9.8, "high": 10.5, "low": 9.8, "close": 9.8}, {"time": "2025-10-08", "open": 9.6, "high": 9.6, "low": 9.6, "close": 9.6}, {"time": "2025-10-09", "open": 9.4, "high": 9.4, "low": 9.4, "close": 9.4}, {"time": "2025-10-12", "open": 9.6, "high": 9.6, "low": 9.2, "close": 9.2}, {"time": "2025-10-13", "open": 9.1, "high": 9.1, "low": 9.1, "close": 9.1}, {"time": "2025-10-16", "open": 9.2, "high": 9.2, "low": 9.2, "close": 9.2}, {"time": "2025-10-19", "open": 9.1, "high": 9.1, "low": 9.1, "close": 9.1}, {"time": "2025-10-26", "open": 9.1, "high": 9.2, "low": 9.0, "close": 9.0}, {"time": "2025-10-28", "open": 9.2, "high": 9.4, "low": 9.2, "close": 9.4}, {"time": "2025-10-29", "open": 9.2, "high": 9.2, "low": 9.2, "close": 9.2}, {"time": "2025-11-02", "open": 9.2, "high": 9.2, "low": 9.2, "close": 9.2}, {"time": "2025-11-03", "open": 9.3, "high": 9.4, "low": 9.3, "close": 9.4}, {"time": "2025-11-04", "open": 9.2, "high": 9.2, "low": 9.2, "close": 9.2}, {"time": "2025-11-06", "open": 9.1, "high": 9.4, "low": 9.1, "close": 9.4}, {"time": "2025-11-09", "open": 9.3, "high": 9.4, "low": 9.2, "close": 9.2}, {"time": "2025-11-10", "open": 9.3, "high": 9.3, "low": 9.3, "close": 9.3}, {"time": "2025-11-11", "open": 9.2, "high": 9.3, "low": 9.2, "close": 9.3}, {"time": "2025-11-12", "open": 9.2, "high": 9.2, "low": 9.2, "close": 9.2}, {"time": "2025-11-16", "open": 9.0, "high": 9.2, "low": 9.0, "close": 9.2}, {"time": "2025-11-17", "open": 9.1, "high": 9.1, "low": 9.0, "close": 9.0}, {"time": "2025-11-18", "open": 9.2, "high": 9.2, "low": 9.2, "close": 9.2}, {"time": "2025-11-19", "open": 9.4, "high": 9.4, "low": 9.0, "close": 9.0}, {"time": "2025-11-20", "open": 9.0, "high": 9.1, "low": 8.9, "close": 9.1}, {"time": "2025-11-24", "open": 9.1, "high": 9.1, "low": 9.1, "close": 9.1}, {"time": "2025-11-25", "open": 9.1, "high": 9.1, "low": 9.1, "close": 9.1}, {"time": "2025-11-26", "open": 9.2, "high": 9.3, "low": 9.2, "close": 9.3}, {"time": "2025-11-27", "open": 9.3, "high": 9.3, "low": 9.3, "close": 9.3}, {"time": "2025-11-30", "open": 9.3, "high": 9.3, "low": 9.3, "close": 9.3}, {"time": "2025-12-01", "open": 9.5, "high": 9.5, "low": 9.5, "close": 9.5}, {"time": "2025-12-02", "open": 9.6, "high": 9.6, "low": 9.3, "close": 9.3}, {"time": "2025-12-03", "open": 9.5, "high": 9.5, "low": 9.5, "close": 9.5}, {"time": "2025-12-07", "open": 9.6, "high": 9.6, "low": 9.6, "close": 9.6}, {"time": "2025-12-08", "open": 9.6, "high": 9.6, "low": 9.4, "close": 9.4}, {"time": "2025-12-09", "open": 9.2, "high": 9.3, "low": 9.2, "close": 9.3}, {"time": "2025-12-10", "open": 9.4, "high": 9.4, "low": 9.3, "close": 9.3}, {"time": "2025-12-11", "open": 9.2, "high": 9.4, "low": 9.2, "close": 9.4}, {"time": "2025-12-14", "open": 9.3, "high": 9.5, "low": 9.3, "close": 9.4}, {"time": "2025-12-15", "open": 9.6, "high": 9.6, "low": 9.4, "close": 9.4}, {"time": "2025-12-16", "open": 9.4, "high": 9.4, "low": 9.4, "close": 9.4}, {"time": "2025-12-17", "open": 9.4, "high": 9.5, "low": 9.4, "close": 9.4}, {"time": "2025-12-18", "open": 9.6, "high": 9.6, "low": 9.6, "close": 9.6}, {"time": "2025-12-21", "open": 9.4, "high": 9.4, "low": 9.4, "close": 9.4}, {"time": "2025-12-22", "open": 9.6, "high": 9.8, "low": 9.6, "close": 9.8}, {"time": "2025-12-23", "open": 9.9, "high": 9.9, "low": 9.7, "close": 9.7}, {"time": "2025-12-24", "open": 9.5, "high": 9.7, "low": 9.5, "close": 9.6}, {"time": "2025-12-28", "open": 9.8, "high": 9.8, "low": 9.6, "close": 9.7}, {"time": "2025-12-29", "open": 9.6, "high": 9.6, "low": 9.6, "close": 9.6}, {"time": "2025-12-31", "open": 9.4, "high": 9.8, "low": 9.4, "close": 9.8}, {"time": "2026-01-01", "open": 9.8, "high": 9.8, "low": 9.8, "close": 9.8}, {"time": "2026-01-04", "open": 9.8, "high": 9.9, "low": 9.8, "close": 9.8}, {"time": "2026-01-05", "open": 9.6, "high": 9.8, "low": 9.6, "close": 9.8}, {"time": "2026-01-06", "open": 9.9, "high": 9.9, "low": 9.8, "close": 9.8}, {"time": "2026-01-07", "open": 9.8, "high": 9.9, "low": 9.7, "close": 9.7}, {"time": "2026-01-08", "open": 9.9, "high": 9.9, "low": 9.9, "close": 9.9}, {"time": "2026-01-12", "open": 10.0, "high": 10.0, "low": 9.8, "close": 9.8}, {"time": "2026-01-13", "open": 10.0, "high": 10.0, "low": 9.7, "close": 9.8}, {"time": "2026-01-14", "open": 9.8, "high": 9.8, "low": 9.7, "close": 9.7}, {"time": "2026-01-18", "open": 9.5, "high": 10.0, "low": 9.5, "close": 10.0}, {"time": "2026-01-20", "open": 9.8, "high": 9.8, "low": 9.8, "close": 9.8}, {"time": "2026-01-21", "open": 10.0, "high": 10.0, "low": 9.7, "close": 9.7}, {"time": "2026-01-22", "open": 9.9, "high": 10.1, "low": 9.9, "close": 9.9}, {"time": "2026-01-25", "open": 10.0, "high": 10.0, "low": 10.0, "close": 10.0}, {"time": "2026-01-26", "open": 9.8, "high": 10.1, "low": 9.8, "close": 10.1}, {"time": "2026-01-27", "open": 10.0, "high": 10.0, "low": 9.8, "close": 9.8}, {"time": "2026-01-28", "open": 9.8, "high": 10.0, "low": 9.8, "close": 10.0}, {"time": "2026-01-29", "open": 10.1, "high": 10.1, "low": 10.0, "close": 10.0}, {"time": "2026-02-01", "open": 9.8, "high": 9.8, "low": 9.8, "close": 9.8}, {"time": "2026-02-02", "open": 9.6, "high": 9.8, "low": 9.6, "close": 9.7}, {"time": "2026-02-04", "open": 9.6, "high": 9.8, "low": 9.6, "close": 9.8}, {"time": "2026-02-05", "open": 9.8, "high": 10.0, "low": 9.8, "close": 9.8}, {"time": "2026-02-08", "open": 9.8, "high": 9.8, "low": 9.7, "close": 9.7}, {"time": "2026-02-09", "open": 9.6, "high": 9.8, "low": 9.6, "close": 9.8}, {"time": "2026-02-10", "open": 9.6, "high": 9.6, "low": 9.6, "close": 9.6}, {"time": "2026-02-11", "open": 9.6, "high": 9.8, "low": 9.6, "close": 9.8}, {"time": "2026-02-12", "open": 9.7, "high": 9.7, "low": 9.7, "close": 9.7}, {"time": "2026-02-16", "open": 9.8, "high": 9.9, "low": 9.8, "close": 9.9}, {"time": "2026-02-17", "open": 9.7, "high": 9.7, "low": 9.7, "close": 9.7}, {"time": "2026-02-22", "open": 9.9, "high": 9.9, "low": 9.9, "close": 9.9}, {"time": "2026-02-23", "open": 9.7, "high": 9.7, "low": 9.7, "close": 9.7}, {"time": "2026-02-25", "open": 9.9, "high": 9.9, "low": 9.7, "close": 9.9}, {"time": "2026-02-26", "open": 9.7, "high": 9.7, "low": 9.7, "close": 9.7}, {"time": "2026-03-01", "open": 9.5, "high": 9.6, "low": 9.5, "close": 9.6}, {"time": "2026-03-03", "open": 9.5, "high": 9.5, "low": 9.5, "close": 9.5}, {"time": "2026-03-10", "open": 9.7, "high": 9.8, "low": 9.5, "close": 9.7}, {"time": "2026-03-11", "open": 9.9, "high": 10.2, "low": 9.9, "close": 10.2}, {"time": "2026-03-12", "open": 10.2, "high": 10.4, "low": 10.2, "close": 10.4}, {"time": "2026-03-15", "open": 10.2, "high": 10.2, "low": 10.0, "close": 10.0}, {"time": "2026-03-16", "open": 10.0, "high": 10.0, "low": 9.8, "close": 10.0}, {"time": "2026-03-17", "open": 10.0, "high": 10.0, "low": 9.8, "close": 9.8}, {"time": "2026-03-19", "open": 10.0, "high": 10.0, "low": 9.8, "close": 10.0}, {"time": "2026-03-22", "open": 9.8, "high": 10.6, "low": 9.8, "close": 10.6}, {"time": "2026-03-23", "open": 10.6, "high": 10.8, "low": 10.6, "close": 10.6}, {"time": "2026-03-24", "open": 10.4, "high": 10.4, "low": 10.3, "close": 10.3}, {"time": "2026-03-25", "open": 10.2, "high": 10.2, "low": 10.1, "close": 10.1}, {"time": "2026-03-26", "open": 10.2, "high": 10.4, "low": 10.2, "close": 10.2}, {"time": "2026-03-27", "open": 10.2, "high": 10.4, "low": 10.2, "close": 10.2}, {"time": "2026-03-30", "open": 10.2, "high": 10.2, "low": 10.1, "close": 10.1}, {"time": "2026-03-31", "open": 10.0, "high": 10.0, "low": 9.9, "close": 10.0}, {"time": "2026-04-01", "open": 10.2, "high": 10.2, "low": 10.0, "close": 10.0}, {"time": "2026-04-06", "open": 10.4, "high": 10.4, "low": 10.4, "close": 10.4}, {"time": "2026-04-07", "open": 10.2, "high": 10.2, "low": 10.2, "close": 10.2}, {"time": "2026-04-08", "open": 10.1, "high": 10.1, "low": 10.1, "close": 10.1}, {"time": "2026-04-09", "open": 10.2, "high": 10.2, "low": 10.0, "close": 10.0}, {"time": "2026-04-12", "open": 10.1, "high": 10.1, "low": 10.1, "close": 10.1}, {"time": "2026-04-13", "open": 10.1, "high": 10.1, "low": 10.1, "close": 10.1}, {"time": "2026-04-14", "open": 10.1, "high": 10.1, "low": 10.1, "close": 10.1}, {"time": "2026-04-15", "open": 10.3, "high": 10.5, "low": 10.3, "close": 10.3}, {"time": "2026-04-16", "open": 10.5, "high": 10.5, "low": 10.4, "close": 10.4}, {"time": "2026-04-19", "open": 10.5, "high": 10.5, "low": 10.3, "close": 10.3}, {"time": "2026-04-20", "open": 10.2, "high": 10.2, "low": 10.2, "close": 10.2}, {"time": "2026-04-21", "open": 10.2, "high": 10.4, "low": 10.2, "close": 10.2}, {"time": "2026-04-22", "open": 10.2, "high": 10.2, "low": 10.2, "close": 10.2}], "volumes": [{"time": "2024-09-02", "value": 71545, "color": "rgba(255,82,82,0.5)"}, {"time": "2024-09-03", "value": 51600, "color": "rgba(0,228,117,0.5)"}, {"time": "2024-09-04", "value": 11225, "color": "rgba(0,228,117,0.5)"}, {"time": "2024-09-05", "value": 69261, "color": "rgba(255,82,82,0.5)"}, {"time": "2024-09-08", "value": 416776, "color": "rgba(0,228,117,0.5)"}, {"time": "2024-09-09", "value": 10100, "color": "rgba(255,82,82,0.5)"}, {"time": "2024-09-10", "value": 2600, "color": "rgba(0,228,117,0.5)"}, {"time": "2024-09-12", "value": 5100, "color": "rgba(0,228,117,0.5)"}, {"time": "2024-09-15", "value": 44205, "color": "rgba(255,82,82,0.5)"}, {"time": "2024-09-16", "value": 30000, "color": "rgba(255,82,82,0.5)"}, {"time": "2024-09-18", "value": 54600, "color": "rgba(255,82,82,0.5)"}, {"time": "2024-09-22", "value": 16199, "color": "rgba(0,228,117,0.5)"}, {"time": "2024-09-23", "value": 300, "color": "rgba(0,228,117,0.5)"}, {"time": "2024-09-24", "value": 1800, "color": "rgba(255,82,82,0.5)"}, {"time": "2024-09-25", "value": 700, "color": "rgba(0,228,117,0.5)"}, {"time": "2024-09-26", "value": 100, "color": "rgba(0,228,117,0.5)"}, {"time": "2024-09-30", "value": 2800, "color": "rgba(0,228,117,0.5)"}, {"time": "2024-10-01", "value": 6278, "color": "rgba(0,228,117,0.5)"}, {"time": "2024-10-02", "value": 3700, "color": "rgba(255,82,82,0.5)"}, {"time": "2024-10-06", "value": 1485, "color": "rgba(0,228,117,0.5)"}, {"time": "2024-10-07", "value": 56200, "color": "rgba(255,82,82,0.5)"}, {"time": "2024-10-08", "value": 38050, "color": "rgba(0,228,117,0.5)"}, {"time": "2024-10-15", "value": 37162, "color": "rgba(0,228,117,0.5)"}, {"time": "2024-10-16", "value": 114120, "color": "rgba(0,228,117,0.5)"}, {"time": "2024-10-17", "value": 74770, "color": "rgba(255,82,82,0.5)"}, {"time": "2024-10-20", "value": 228000, "color": "rgba(255,82,82,0.5)"}, {"time": "2024-10-21", "value": 225606, "color": "rgba(0,228,117,0.5)"}, {"time": "2024-10-22", "value": 1111, "color": "rgba(0,228,117,0.5)"}, {"time": "2024-10-23", "value": 186174, "color": "rgba(255,82,82,0.5)"}, {"time": "2024-10-24", "value": 144576, "color": "rgba(255,82,82,0.5)"}, {"time": "2024-10-27", "value": 1000, "color": "rgba(255,82,82,0.5)"}, {"time": "2024-10-28", "value": 3750, "color": "rgba(255,82,82,0.5)"}, {"time": "2024-10-29", "value": 351, "color": "rgba(0,228,117,0.5)"}, {"time": "2024-11-06", "value": 200, "color": "rgba(0,228,117,0.5)"}, {"time": "2024-11-10", "value": 12350, "color": "rgba(255,82,82,0.5)"}, {"time": "2024-11-11", "value": 2200, "color": "rgba(0,228,117,0.5)"}, {"time": "2024-11-12", "value": 19100, "color": "rgba(0,228,117,0.5)"}, {"time": "2024-11-13", "value": 500, "color": "rgba(255,82,82,0.5)"}, {"time": "2024-11-14", "value": 13950, "color": "rgba(0,228,117,0.5)"}, {"time": "2024-11-17", "value": 15050, "color": "rgba(255,82,82,0.5)"}, {"time": "2024-11-19", "value": 147180, "color": "rgba(0,228,117,0.5)"}, {"time": "2024-11-20", "value": 25100, "color": "rgba(0,228,117,0.5)"}, {"time": "2024-11-21", "value": 8625, "color": "rgba(0,228,117,0.5)"}, {"time": "2024-11-24", "value": 3000, "color": "rgba(0,228,117,0.5)"}, {"time": "2024-11-25", "value": 2950, "color": "rgba(0,228,117,0.5)"}, {"time": "2024-11-26", "value": 29150, "color": "rgba(0,228,117,0.5)"}, {"time": "2024-11-27", "value": 17600, "color": "rgba(0,228,117,0.5)"}, {"time": "2024-11-28", "value": 39590, "color": "rgba(0,228,117,0.5)"}, {"time": "2024-12-01", "value": 103000, "color": "rgba(0,228,117,0.5)"}, {"time": "2024-12-02", "value": 2501350, "color": "rgba(0,228,117,0.5)"}, {"time": "2024-12-03", "value": 20600, "color": "rgba(0,228,117,0.5)"}, {"time": "2024-12-04", "value": 6200, "color": "rgba(0,228,117,0.5)"}, {"time": "2024-12-05", "value": 11400, "color": "rgba(0,228,117,0.5)"}, {"time": "2024-12-08", "value": 700, "color": "rgba(255,82,82,0.5)"}, {"time": "2024-12-09", "value": 300, "color": "rgba(0,228,117,0.5)"}, {"time": "2024-12-10", "value": 1072, "color": "rgba(0,228,117,0.5)"}, {"time": "2024-12-11", "value": 4650, "color": "rgba(255,82,82,0.5)"}, {"time": "2024-12-12", "value": 39800, "color": "rgba(0,228,117,0.5)"}, {"time": "2024-12-16", "value": 16900, "color": "rgba(0,228,117,0.5)"}, {"time": "2024-12-17", "value": 10300, "color": "rgba(255,82,82,0.5)"}, {"time": "2024-12-18", "value": 57800, "color": "rgba(255,82,82,0.5)"}, {"time": "2024-12-19", "value": 100, "color": "rgba(0,228,117,0.5)"}, {"time": "2024-12-23", "value": 149646, "color": "rgba(255,82,82,0.5)"}, {"time": "2024-12-24", "value": 6000, "color": "rgba(255,82,82,0.5)"}, {"time": "2024-12-26", "value": 13830, "color": "rgba(0,228,117,0.5)"}, {"time": "2024-12-29", "value": 600, "color": "rgba(0,228,117,0.5)"}, {"time": "2024-12-31", "value": 400, "color": "rgba(0,228,117,0.5)"}, {"time": "2025-01-01", "value": 1700, "color": "rgba(255,82,82,0.5)"}, {"time": "2025-01-02", "value": 600, "color": "rgba(0,228,117,0.5)"}, {"time": "2025-01-05", "value": 1500, "color": "rgba(0,228,117,0.5)"}, {"time": "2025-01-06", "value": 216500, "color": "rgba(0,228,117,0.5)"}, {"time": "2025-01-07", "value": 2900, "color": "rgba(0,228,117,0.5)"}, {"time": "2025-01-08", "value": 15255, "color": "rgba(255,82,82,0.5)"}, {"time": "2025-01-09", "value": 10000, "color": "rgba(255,82,82,0.5)"}, {"time": "2025-01-12", "value": 1000, "color": "rgba(0,228,117,0.5)"}, {"time": "2025-01-13", "value": 3800, "color": "rgba(255,82,82,0.5)"}, {"time": "2025-01-15", "value": 100, "color": "rgba(0,228,117,0.5)"}, {"time": "2025-01-19", "value": 1500, "color": "rgba(0,228,117,0.5)"}, {"time": "2025-01-20", "value": 600, "color": "rgba(0,228,117,0.5)"}, {"time": "2025-01-21", "value": 2800, "color": "rgba(255,82,82,0.5)"}, {"time": "2025-01-22", "value": 6800, "color": "rgba(0,228,117,0.5)"}, {"time": "2025-01-23", "value": 4299, "color": "rgba(0,228,117,0.5)"}, {"time": "2025-01-26", "value": 300, "color": "rgba(0,228,117,0.5)"}, {"time": "2025-01-27", "value": 185289, "color": "rgba(255,82,82,0.5)"}, {"time": "2025-01-28", "value": 10000, "color": "rgba(0,228,117,0.5)"}, {"time": "2025-02-02", "value": 124100, "color": "rgba(0,228,117,0.5)"}, {"time": "2025-02-03", "value": 67361, "color": "rgba(0,228,117,0.5)"}, {"time": "2025-02-04", "value": 6100, "color": "rgba(0,228,117,0.5)"}, {"time": "2025-02-05", "value": 45885, "color": "rgba(255,82,82,0.5)"}, {"time": "2025-02-06", "value": 58700, "color": "rgba(0,228,117,0.5)"}, {"time": "2025-02-09", "value": 76150, "color": "rgba(0,228,117,0.5)"}, {"time": "2025-02-11", "value": 715, "color": "rgba(0,228,117,0.5)"}, {"time": "2025-02-12", "value": 1800, "color": "rgba(0,228,117,0.5)"}, {"time": "2025-02-13", "value": 68400, "color": "rgba(0,228,117,0.5)"}, {"time": "2025-02-16", "value": 37950, "color": "rgba(0,228,117,0.5)"}, {"time": "2025-02-17", "value": 12000, "color": "rgba(0,228,117,0.5)"}, {"time": "2025-02-18", "value": 13900, "color": "rgba(0,228,117,0.5)"}, {"time": "2025-02-20", "value": 36755, "color": "rgba(0,228,117,0.5)"}, {"time": "2025-02-23", "value": 6000, "color": "rgba(0,228,117,0.5)"}, {"time": "2025-02-24", "value": 11650, "color": "rgba(0,228,117,0.5)"}, {"time": "2025-02-25", "value": 2500, "color": "rgba(0,228,117,0.5)"}, {"time": "2025-02-27", "value": 8100, "color": "rgba(255,82,82,0.5)"}, {"time": "2025-03-02", "value": 42100, "color": "rgba(0,228,117,0.5)"}, {"time": "2025-03-03", "value": 267915, "color": "rgba(255,82,82,0.5)"}, {"time": "2025-03-04", "value": 173360, "color": "rgba(0,228,117,0.5)"}, {"time": "2025-03-05", "value": 251860, "color": "rgba(0,228,117,0.5)"}, {"time": "2025-03-06", "value": 16800, "color": "rgba(0,228,117,0.5)"}, {"time": "2025-03-09", "value": 154866, "color": "rgba(0,228,117,0.5)"}, {"time": "2025-03-11", "value": 1100, "color": "rgba(0,228,117,0.5)"}, {"time": "2025-03-12", "value": 2000, "color": "rgba(0,228,117,0.5)"}, {"time": "2025-03-16", "value": 100, "color": "rgba(0,228,117,0.5)"}, {"time": "2025-03-17", "value": 6800, "color": "rgba(255,82,82,0.5)"}, {"time": "2025-03-18", "value": 5900, "color": "rgba(255,82,82,0.5)"}, {"time": "2025-03-19", "value": 17700, "color": "rgba(255,82,82,0.5)"}, {"time": "2025-03-20", "value": 2000, "color": "rgba(255,82,82,0.5)"}, {"time": "2025-03-23", "value": 5700, "color": "rgba(255,82,82,0.5)"}, {"time": "2025-03-24", "value": 2400, "color": "rgba(0,228,117,0.5)"}, {"time": "2025-03-25", "value": 6250, "color": "rgba(0,228,117,0.5)"}, {"time": "2025-03-26", "value": 11700, "color": "rgba(0,228,117,0.5)"}, {"time": "2025-03-27", "value": 30750, "color": "rgba(255,82,82,0.5)"}, {"time": "2025-03-30", "value": 100, "color": "rgba(0,228,117,0.5)"}, {"time": "2025-04-01", "value": 16125, "color": "rgba(0,228,117,0.5)"}, {"time": "2025-04-02", "value": 8314, "color": "rgba(0,228,117,0.5)"}, {"time": "2025-04-03", "value": 10600, "color": "rgba(0,228,117,0.5)"}, {"time": "2025-04-07", "value": 9700, "color": "rgba(0,228,117,0.5)"}, {"time": "2025-04-08", "value": 30200, "color": "rgba(0,228,117,0.5)"}, {"time": "2025-04-09", "value": 2500, "color": "rgba(255,82,82,0.5)"}, {"time": "2025-04-10", "value": 50000, "color": "rgba(0,228,117,0.5)"}, {"time": "2025-04-13", "value": 7800, "color": "rgba(255,82,82,0.5)"}, {"time": "2025-04-15", "value": 109155, "color": "rgba(0,228,117,0.5)"}, {"time": "2025-04-16", "value": 1000, "color": "rgba(0,228,117,0.5)"}, {"time": "2025-04-17", "value": 10000, "color": "rgba(0,228,117,0.5)"}, {"time": "2025-04-20", "value": 12380, "color": "rgba(0,228,117,0.5)"}, {"time": "2025-04-21", "value": 100, "color": "rgba(0,228,117,0.5)"}, {"time": "2025-04-22", "value": 5550, "color": "rgba(0,228,117,0.5)"}, {"time": "2025-04-23", "value": 161475, "color": "rgba(255,82,82,0.5)"}, {"time": "2025-04-24", "value": 151100, "color": "rgba(255,82,82,0.5)"}, {"time": "2025-04-27", "value": 8100, "color": "rgba(0,228,117,0.5)"}, {"time": "2025-04-28", "value": 5100, "color": "rgba(255,82,82,0.5)"}, {"time": "2025-04-29", "value": 7200, "color": "rgba(0,228,117,0.5)"}, {"time": "2025-04-30", "value": 1600, "color": "rgba(0,228,117,0.5)"}, {"time": "2025-05-04", "value": 2500, "color": "rgba(0,228,117,0.5)"}, {"time": "2025-05-05", "value": 200, "color": "rgba(0,228,117,0.5)"}, {"time": "2025-05-06", "value": 1600, "color": "rgba(0,228,117,0.5)"}, {"time": "2025-05-07", "value": 2600, "color": "rgba(0,228,117,0.5)"}, {"time": "2025-05-08", "value": 200, "color": "rgba(0,228,117,0.5)"}, {"time": "2025-05-11", "value": 6100, "color": "rgba(0,228,117,0.5)"}, {"time": "2025-05-13", "value": 100, "color": "rgba(0,228,117,0.5)"}, {"time": "2025-05-15", "value": 2000, "color": "rgba(0,228,117,0.5)"}, {"time": "2025-05-18", "value": 1500, "color": "rgba(0,228,117,0.5)"}, {"time": "2025-05-19", "value": 700, "color": "rgba(0,228,117,0.5)"}, {"time": "2025-05-21", "value": 100, "color": "rgba(0,228,117,0.5)"}, {"time": "2025-05-22", "value": 7500, "color": "rgba(0,228,117,0.5)"}, {"time": "2025-05-25", "value": 3370, "color": "rgba(0,228,117,0.5)"}, {"time": "2025-05-26", "value": 74500, "color": "rgba(0,228,117,0.5)"}, {"time": "2025-05-27", "value": 200, "color": "rgba(0,228,117,0.5)"}, {"time": "2025-05-28", "value": 4670, "color": "rgba(0,228,117,0.5)"}, {"time": "2025-06-02", "value": 100, "color": "rgba(0,228,117,0.5)"}, {"time": "2025-06-03", "value": 5100, "color": "rgba(0,228,117,0.5)"}, {"time": "2025-06-04", "value": 2599, "color": "rgba(0,228,117,0.5)"}, {"time": "2025-06-05", "value": 700, "color": "rgba(255,82,82,0.5)"}, {"time": "2025-06-08", "value": 10250, "color": "rgba(255,82,82,0.5)"}, {"time": "2025-06-09", "value": 500, "color": "rgba(0,228,117,0.5)"}, {"time": "2025-06-10", "value": 600, "color": "rgba(255,82,82,0.5)"}, {"time": "2025-06-11", "value": 11400, "color": "rgba(0,228,117,0.5)"}, {"time": "2025-06-12", "value": 21800, "color": "rgba(0,228,117,0.5)"}, {"time": "2025-06-16", "value": 7100, "color": "rgba(0,228,117,0.5)"}, {"time": "2025-06-17", "value": 75950, "color": "rgba(0,228,117,0.5)"}, {"time": "2025-06-18", "value": 26100, "color": "rgba(255,82,82,0.5)"}, {"time": "2025-06-19", "value": 20000, "color": "rgba(0,228,117,0.5)"}, {"time": "2025-06-22", "value": 17500, "color": "rgba(255,82,82,0.5)"}, {"time": "2025-06-23", "value": 73711, "color": "rgba(0,228,117,0.5)"}, {"time": "2025-06-24", "value": 1000, "color": "rgba(0,228,117,0.5)"}, {"time": "2025-06-25", "value": 43152, "color": "rgba(255,82,82,0.5)"}, {"time": "2025-06-26", "value": 1401, "color": "rgba(0,228,117,0.5)"}, {"time": "2025-06-29", "value": 9900, "color": "rgba(0,228,117,0.5)"}, {"time": "2025-06-30", "value": 1200, "color": "rgba(0,228,117,0.5)"}, {"time": "2025-07-01", "value": 13900, "color": "rgba(255,82,82,0.5)"}, {"time": "2025-07-02", "value": 17200, "color": "rgba(0,228,117,0.5)"}, {"time": "2025-07-03", "value": 400, "color": "rgba(0,228,117,0.5)"}, {"time": "2025-07-06", "value": 47270, "color": "rgba(0,228,117,0.5)"}, {"time": "2025-07-07", "value": 6400, "color": "rgba(255,82,82,0.5)"}, {"time": "2025-07-08", "value": 300, "color": "rgba(0,228,117,0.5)"}, {"time": "2025-07-09", "value": 26800, "color": "rgba(255,82,82,0.5)"}, {"time": "2025-07-10", "value": 122561, "color": "rgba(0,228,117,0.5)"}, {"time": "2025-07-13", "value": 11500, "color": "rgba(0,228,117,0.5)"}, {"time": "2025-07-14", "value": 133913, "color": "rgba(0,228,117,0.5)"}, {"time": "2025-07-15", "value": 302300, "color": "rgba(0,228,117,0.5)"}, {"time": "2025-07-16", "value": 41770, "color": "rgba(255,82,82,0.5)"}, {"time": "2025-07-17", "value": 35800, "color": "rgba(0,228,117,0.5)"}, {"time": "2025-07-20", "value": 32800, "color": "rgba(0,228,117,0.5)"}, {"time": "2025-07-21", "value": 19000, "color": "rgba(0,228,117,0.5)"}, {"time": "2025-07-22", "value": 92300, "color": "rgba(0,228,117,0.5)"}, {"time": "2025-07-23", "value": 101600, "color": "rgba(0,228,117,0.5)"}, {"time": "2025-07-24", "value": 1000, "color": "rgba(0,228,117,0.5)"}, {"time": "2025-07-27", "value": 20300, "color": "rgba(0,228,117,0.5)"}, {"time": "2025-07-28", "value": 35000, "color": "rgba(0,228,117,0.5)"}, {"time": "2025-07-29", "value": 34190, "color": "rgba(0,228,117,0.5)"}, {"time": "2025-07-30", "value": 178600, "color": "rgba(255,82,82,0.5)"}, {"time": "2025-07-31", "value": 553387, "color": "rgba(0,228,117,0.5)"}, {"time": "2025-08-03", "value": 16350, "color": "rgba(255,82,82,0.5)"}, {"time": "2025-08-04", "value": 3200, "color": "rgba(0,228,117,0.5)"}, {"time": "2025-08-05", "value": 20700, "color": "rgba(0,228,117,0.5)"}, {"time": "2025-08-06", "value": 1100, "color": "rgba(0,228,117,0.5)"}, {"time": "2025-08-07", "value": 25100, "color": "rgba(0,228,117,0.5)"}, {"time": "2025-08-11", "value": 923549, "color": "rgba(0,228,117,0.5)"}, {"time": "2025-08-12", "value": 229516, "color": "rgba(0,228,117,0.5)"}, {"time": "2025-08-13", "value": 31650, "color": "rgba(0,228,117,0.5)"}, {"time": "2025-08-14", "value": 276193, "color": "rgba(255,82,82,0.5)"}, {"time": "2025-08-17", "value": 789750, "color": "rgba(0,228,117,0.5)"}, {"time": "2025-08-18", "value": 48400, "color": "rgba(255,82,82,0.5)"}, {"time": "2025-08-19", "value": 47340, "color": "rgba(0,228,117,0.5)"}, {"time": "2025-08-20", "value": 324596, "color": "rgba(255,82,82,0.5)"}, {"time": "2025-08-21", "value": 728290, "color": "rgba(0,228,117,0.5)"}, {"time": "2025-08-24", "value": 129300, "color": "rgba(255,82,82,0.5)"}, {"time": "2025-08-25", "value": 12700, "color": "rgba(0,228,117,0.5)"}, {"time": "2025-08-26", "value": 22465, "color": "rgba(0,228,117,0.5)"}, {"time": "2025-08-27", "value": 200, "color": "rgba(0,228,117,0.5)"}, {"time": "2025-08-28", "value": 343200, "color": "rgba(255,82,82,0.5)"}, {"time": "2025-08-31", "value": 1750, "color": "rgba(0,228,117,0.5)"}, {"time": "2025-09-01", "value": 37788, "color": "rgba(255,82,82,0.5)"}, {"time": "2025-09-02", "value": 100, "color": "rgba(0,228,117,0.5)"}, {"time": "2025-09-03", "value": 24100, "color": "rgba(255,82,82,0.5)"}, {"time": "2025-09-04", "value": 74350, "color": "rgba(0,228,117,0.5)"}, {"time": "2025-09-07", "value": 4580, "color": "rgba(0,228,117,0.5)"}, {"time": "2025-09-08", "value": 17950, "color": "rgba(255,82,82,0.5)"}, {"time": "2025-09-21", "value": 3100, "color": "rgba(0,228,117,0.5)"}, {"time": "2025-09-23", "value": 500, "color": "rgba(0,228,117,0.5)"}, {"time": "2025-09-24", "value": 68600, "color": "rgba(0,228,117,0.5)"}, {"time": "2025-09-25", "value": 36700, "color": "rgba(0,228,117,0.5)"}, {"time": "2025-09-28", "value": 457350, "color": "rgba(0,228,117,0.5)"}, {"time": "2025-10-08", "value": 3000, "color": "rgba(0,228,117,0.5)"}, {"time": "2025-10-09", "value": 2650, "color": "rgba(0,228,117,0.5)"}, {"time": "2025-10-12", "value": 1650, "color": "rgba(255,82,82,0.5)"}, {"time": "2025-10-13", "value": 500, "color": "rgba(0,228,117,0.5)"}, {"time": "2025-10-16", "value": 7000, "color": "rgba(0,228,117,0.5)"}, {"time": "2025-10-19", "value": 1000, "color": "rgba(0,228,117,0.5)"}, {"time": "2025-10-26", "value": 7300, "color": "rgba(255,82,82,0.5)"}, {"time": "2025-10-28", "value": 1300, "color": "rgba(0,228,117,0.5)"}, {"time": "2025-10-29", "value": 1600, "color": "rgba(0,228,117,0.5)"}, {"time": "2025-11-02", "value": 4800, "color": "rgba(0,228,117,0.5)"}, {"time": "2025-11-03", "value": 9000, "color": "rgba(0,228,117,0.5)"}, {"time": "2025-11-04", "value": 100, "color": "rgba(0,228,117,0.5)"}, {"time": "2025-11-06", "value": 19750, "color": "rgba(0,228,117,0.5)"}, {"time": "2025-11-09", "value": 6200, "color": "rgba(255,82,82,0.5)"}, {"time": "2025-11-10", "value": 2000, "color": "rgba(0,228,117,0.5)"}, {"time": "2025-11-11", "value": 10700, "color": "rgba(0,228,117,0.5)"}, {"time": "2025-11-12", "value": 7400, "color": "rgba(0,228,117,0.5)"}, {"time": "2025-11-16", "value": 12220, "color": "rgba(0,228,117,0.5)"}, {"time": "2025-11-17", "value": 7400, "color": "rgba(255,82,82,0.5)"}, {"time": "2025-11-18", "value": 11400, "color": "rgba(0,228,117,0.5)"}, {"time": "2025-11-19", "value": 68810, "color": "rgba(255,82,82,0.5)"}, {"time": "2025-11-20", "value": 7450, "color": "rgba(0,228,117,0.5)"}, {"time": "2025-11-24", "value": 2500, "color": "rgba(0,228,117,0.5)"}, {"time": "2025-11-25", "value": 1199, "color": "rgba(0,228,117,0.5)"}, {"time": "2025-11-26", "value": 3430, "color": "rgba(0,228,117,0.5)"}, {"time": "2025-11-27", "value": 300, "color": "rgba(0,228,117,0.5)"}, {"time": "2025-11-30", "value": 100, "color": "rgba(0,228,117,0.5)"}, {"time": "2025-12-01", "value": 200, "color": "rgba(0,228,117,0.5)"}, {"time": "2025-12-02", "value": 50300, "color": "rgba(255,82,82,0.5)"}, {"time": "2025-12-03", "value": 1000, "color": "rgba(0,228,117,0.5)"}, {"time": "2025-12-07", "value": 5000, "color": "rgba(0,228,117,0.5)"}, {"time": "2025-12-08", "value": 10500, "color": "rgba(255,82,82,0.5)"}, {"time": "2025-12-09", "value": 3816, "color": "rgba(0,228,117,0.5)"}, {"time": "2025-12-10", "value": 850, "color": "rgba(255,82,82,0.5)"}, {"time": "2025-12-11", "value": 34714, "color": "rgba(0,228,117,0.5)"}, {"time": "2025-12-14", "value": 7100, "color": "rgba(0,228,117,0.5)"}, {"time": "2025-12-15", "value": 700, "color": "rgba(255,82,82,0.5)"}, {"time": "2025-12-16", "value": 100, "color": "rgba(0,228,117,0.5)"}, {"time": "2025-12-17", "value": 16600, "color": "rgba(0,228,117,0.5)"}, {"time": "2025-12-18", "value": 3400, "color": "rgba(0,228,117,0.5)"}, {"time": "2025-12-21", "value": 452980, "color": "rgba(0,228,117,0.5)"}, {"time": "2025-12-22", "value": 2200, "color": "rgba(0,228,117,0.5)"}, {"time": "2025-12-23", "value": 16750, "color": "rgba(255,82,82,0.5)"}, {"time": "2025-12-24", "value": 11100, "color": "rgba(0,228,117,0.5)"}, {"time": "2025-12-28", "value": 110515, "color": "rgba(255,82,82,0.5)"}, {"time": "2025-12-29", "value": 10900, "color": "rgba(0,228,117,0.5)"}, {"time": "2025-12-31", "value": 10900, "color": "rgba(0,228,117,0.5)"}, {"time": "2026-01-01", "value": 100925, "color": "rgba(0,228,117,0.5)"}, {"time": "2026-01-04", "value": 42675, "color": "rgba(0,228,117,0.5)"}, {"time": "2026-01-05", "value": 85300, "color": "rgba(0,228,117,0.5)"}, {"time": "2026-01-06", "value": 5200, "color": "rgba(255,82,82,0.5)"}, {"time": "2026-01-07", "value": 163345, "color": "rgba(255,82,82,0.5)"}, {"time": "2026-01-08", "value": 3000, "color": "rgba(0,228,117,0.5)"}, {"time": "2026-01-12", "value": 6750, "color": "rgba(255,82,82,0.5)"}, {"time": "2026-01-13", "value": 9600, "color": "rgba(255,82,82,0.5)"}, {"time": "2026-01-14", "value": 12110, "color": "rgba(255,82,82,0.5)"}, {"time": "2026-01-18", "value": 11600, "color": "rgba(0,228,117,0.5)"}, {"time": "2026-01-20", "value": 2200, "color": "rgba(0,228,117,0.5)"}, {"time": "2026-01-21", "value": 20200, "color": "rgba(255,82,82,0.5)"}, {"time": "2026-01-22", "value": 4350, "color": "rgba(0,228,117,0.5)"}, {"time": "2026-01-25", "value": 6000, "color": "rgba(0,228,117,0.5)"}, {"time": "2026-01-26", "value": 12001, "color": "rgba(0,228,117,0.5)"}, {"time": "2026-01-27", "value": 5100, "color": "rgba(255,82,82,0.5)"}, {"time": "2026-01-28", "value": 10200, "color": "rgba(0,228,117,0.5)"}, {"time": "2026-01-29", "value": 11200, "color": "rgba(255,82,82,0.5)"}, {"time": "2026-02-01", "value": 7000, "color": "rgba(0,228,117,0.5)"}, {"time": "2026-02-02", "value": 11277, "color": "rgba(0,228,117,0.5)"}, {"time": "2026-02-04", "value": 1276, "color": "rgba(0,228,117,0.5)"}, {"time": "2026-02-05", "value": 40200, "color": "rgba(0,228,117,0.5)"}, {"time": "2026-02-08", "value": 10250, "color": "rgba(255,82,82,0.5)"}, {"time": "2026-02-09", "value": 1950, "color": "rgba(0,228,117,0.5)"}, {"time": "2026-02-10", "value": 1000, "color": "rgba(0,228,117,0.5)"}, {"time": "2026-02-11", "value": 5000, "color": "rgba(0,228,117,0.5)"}, {"time": "2026-02-12", "value": 400, "color": "rgba(0,228,117,0.5)"}, {"time": "2026-02-16", "value": 15700, "color": "rgba(0,228,117,0.5)"}, {"time": "2026-02-17", "value": 800, "color": "rgba(0,228,117,0.5)"}, {"time": "2026-02-22", "value": 3000, "color": "rgba(0,228,117,0.5)"}, {"time": "2026-02-23", "value": 100, "color": "rgba(0,228,117,0.5)"}, {"time": "2026-02-25", "value": 1100, "color": "rgba(0,228,117,0.5)"}, {"time": "2026-02-26", "value": 13400, "color": "rgba(0,228,117,0.5)"}, {"time": "2026-03-01", "value": 10300, "color": "rgba(0,228,117,0.5)"}, {"time": "2026-03-03", "value": 200, "color": "rgba(0,228,117,0.5)"}, {"time": "2026-03-10", "value": 21295, "color": "rgba(0,228,117,0.5)"}, {"time": "2026-03-11", "value": 1600, "color": "rgba(0,228,117,0.5)"}, {"time": "2026-03-12", "value": 20000, "color": "rgba(0,228,117,0.5)"}, {"time": "2026-03-15", "value": 18300, "color": "rgba(255,82,82,0.5)"}, {"time": "2026-03-16", "value": 3100, "color": "rgba(0,228,117,0.5)"}, {"time": "2026-03-17", "value": 30000, "color": "rgba(255,82,82,0.5)"}, {"time": "2026-03-19", "value": 52625, "color": "rgba(0,228,117,0.5)"}, {"time": "2026-03-22", "value": 63292, "color": "rgba(0,228,117,0.5)"}, {"time": "2026-03-23", "value": 50198, "color": "rgba(0,228,117,0.5)"}, {"time": "2026-03-24", "value": 8000, "color": "rgba(255,82,82,0.5)"}, {"time": "2026-03-25", "value": 5003, "color": "rgba(255,82,82,0.5)"}, {"time": "2026-03-26", "value": 10100, "color": "rgba(0,228,117,0.5)"}, {"time": "2026-03-27", "value": 10100, "color": "rgba(0,228,117,0.5)"}, {"time": "2026-03-30", "value": 12700, "color": "rgba(255,82,82,0.5)"}, {"time": "2026-03-31", "value": 17979, "color": "rgba(0,228,117,0.5)"}, {"time": "2026-04-01", "value": 31100, "color": "rgba(255,82,82,0.5)"}, {"time": "2026-04-06", "value": 300, "color": "rgba(0,228,117,0.5)"}, {"time": "2026-04-07", "value": 500, "color": "rgba(0,228,117,0.5)"}, {"time": "2026-04-08", "value": 19145, "color": "rgba(0,228,117,0.5)"}, {"time": "2026-04-09", "value": 7800, "color": "rgba(255,82,82,0.5)"}, {"time": "2026-04-12", "value": 6500, "color": "rgba(0,228,117,0.5)"}, {"time": "2026-04-13", "value": 100, "color": "rgba(0,228,117,0.5)"}, {"time": "2026-04-14", "value": 100, "color": "rgba(0,228,117,0.5)"}, {"time": "2026-04-15", "value": 1900, "color": "rgba(0,228,117,0.5)"}, {"time": "2026-04-16", "value": 1100, "color": "rgba(255,82,82,0.5)"}, {"time": "2026-04-19", "value": 3755, "color": "rgba(255,82,82,0.5)"}, {"time": "2026-04-20", "value": 23000, "color": "rgba(0,228,117,0.5)"}, {"time": "2026-04-21", "value": 3800, "color": "rgba(0,228,117,0.5)"}, {"time": "2026-04-22", "value": 500, "color": "rgba(0,228,117,0.5)"}]}